{
    "id": "TECH_TRAPPING",
    "display_key": "TECH_TRAPPING",
    "description_key": "TECH_TRAPPING_DESC",
    "era": "stone_age",
    "tier": 0,
    "categories": ["food_production", "animal"],
    "tags": ["trapping", "hunting", "passive", "snare"],
    "knowledge_type": "universal_intuitive",
    "prereq_logic": {"all_of": ["TECH_BASIC_TOOLS"], "any_of": [], "soft": []},
    "requirements": {"biomes_nearby": [], "resources_nearby": [], "settlement_tags": [], "institution_tags": [], "infrastructure_tags": []},
    "discovery": {
        "base_chance_per_year": 0.25,
        "required_skills": {},
        "required_population": 3,
        "required_cooperation": 0,
        "modifiers": {"knowledge_value": 0.10, "openness": 0.10, "logical_intel": 0.10, "curiosity": 0.0, "naturalistic_intel": 0.0},
        "eureka": false,
        "eureka_conditions": {}
    },
    "maintenance": {"min_practitioners": 1, "regression_grace_years": 40, "carrier_roles": [], "requires_active_use": false, "active_use_threshold": 0.0, "artifact_carriers": [], "institution_tags_help": []},
    "branching": {"branch_family_id": "", "branches_from": "", "branch_type": "", "mutually_exclusive_with": [], "selection_weights": {}},
    "diffusion": {"can_spread": true, "spread_channels": ["trade", "migration"], "adoption_contact_years": 0, "prestige_bias": 0.0, "conformist_bias": 0.0},
    "unlocks": {"skills": ["SKILL_TRAPPING"], "buildings": [], "jobs": ["trapper"], "actions": [], "techs_enabled": []},
    "effects": {"food_yield_hunting": 0.2, "passive_food": 0.15},
    "regression_fallback": "",
    "ui": {"group": "Food Production", "subgroup": "Hunting", "icon": "icon_trapping", "tree_x": 1, "tree_y": 7}
}
