{
  "id": "FACET_A_GENTLENESS",
  "display_key": "FACET_A_GENTLENESS",
  "category": "PERSONALITY_FACET",
  "storage_type": "int",
  "range": [
    0,
    1000
  ],
  "default": 500,
  "tier": 0,
  "growth": {
    "type": "SCURVE",
    "params": {
      "phase_breakpoints": [
        300,
        700
      ],
      "phase_speeds": [
        1.5,
        1.0,
        0.3
      ]
    }
  },
  "thresholds": [
    {
      "value": 850,
      "direction": "above",
      "effect": "TRAIT_FACET_A_GENTLENESS_HIGH",
      "hysteresis": 30
    },
    {
      "value": 150,
      "direction": "below",
      "effect": "TRAIT_FACET_A_GENTLENESS_LOW",
      "hysteresis": 30
    }
  ],
  "affects": [
    {
      "target": "aggression_prob",
      "evaluator": "CURVE",
      "curve": "LINEAR",
      "weight": 0.4,
      "direction": "negative",
      "context": ""
    },
    {
      "target": "comfort_give_prob",
      "evaluator": "CURVE",
      "curve": "LINEAR",
      "weight": 0.3,
      "direction": "positive",
      "context": ""
    }
  ],
  "display": {
    "visible": true,
    "show_in_panel": "personality",
    "descriptor_table": "7_step"
  }
}
